[{"planner_data":{"id": "82b0e849-6450-4960-8c3b-3291e6bcb2d1", "status": "Draft", "flights": [{"id": "f51f4287-16e1-4250-9ae4-7f74b70d6a85", "pnr": "", "baggage": "20kg", "travelClass": "Business", "ticketIssued": false, "ticketNumber": "", "numberOfSeats": 3, "mealPreference": "Standard", "airlineSelected": "", "dateFlexibility": "Flexible (+/- 2 Days)", "paymentReceived": false, "departureCountry": "", "refundableStatus": "Non-Refundable", "customerConfirmed": false, "preferredAirlines": "", "bookingConfirmationUrl": "", "paymentConfirmationUrl": ""}], "profile": {"adults": 2, "infants": 1, "children": 1, "arrivalDate": "2026-06-27", "budgetTotal": 12000, "travelStyle": "Luxury", "durationDays": 8, "departureDate": "2026-07-04", "budgetPerPerson": 6000, "specialConditions": {"dietary": "", "medical": "", "language": "English", "occasion": "Inquiry Type: Super Luxury VIP Experience\n\nMessage: sdsd", "accessibility": ""}}, "summary": {"totalCities": 11, "activityTypeMix": {"General": 7}, "totalActivities": 7, "totalDistanceKm": 915}, "itinerary": [{"id": "0157cbb9-155f-43bb-ad53-e079e658cd4d", "lng": 79.8853, "name": "Arrival at Katunayake Airport (KTA)", "type": "wait", "endTime": "08:00 AM", "distance": null, "dayNumber": 1, "startTime": "07:00 AM", "bufferMins": 15, "locationName": "Katunayake Airport", "durationHours": 1, "internalNotes": "", "paymentStatus": "Pending", "clientVisibleNotes": "", "confirmationStatus": "Pending"}, {"id": "87e686c9-f431-4f09-b4f2-b28d7783126f", "name": "Travel to Anuradhapura", "type": "travel", "endTime": "01:00 PM", "distance": "160 km", "dayNumber": 1, "startTime": "08:00 AM", "bufferMins": 15, "locationName": "Anuradhapura", "durationHours": 5, "internalNotes": "", "paymentStatus": "Pending", "clientVisibleNotes": "", "confirmationStatus": "Pending"}, {"id": "8012c3dc-8837-4de2-90c1-6b67bba30c8b", "name": "Lunch (en route or upon arrival)", "type": "meal", "endTime": "02:30 PM", "dayNumber": 1, "startTime": "01:30 PM", "bufferMins": 15, "locationName": "Anuradhapura", "durationHours": 1, "internalNotes": "", "paymentStatus": "Pending", "clientVisibleNotes": "", "confirmationStatus": "Pending"}, {"id": "0a5d8e1b-3e32-4cc6-b368-fa12194c8c9e", "name": "Travel to Trincomalee", "type": "travel", "endTime": "04:00 PM", "distance": "65 km", "dayNumber": 1, "startTime": "02:30 PM", "bufferMins": 15, "locationName": "Trincomalee", "durationHours": 1, "internalNotes": "", "paymentStatus": "Pending", "clientVisibleNotes": "", "confirmationStatus": "Pending"}, {"id": "6f0d9d21-50ed-4f27-9c62-303a5c72ab0e", "lat": 8.581, "lng": 81.245, "name": "Koneswaram Temple", "type": "activity", "endTime": "06:00 PM", "dayNumber": 1, "startTime": "04:00 PM", "bufferMins": 0, "locationName": "Trincomalee", "durationHours": 1.5, "internalNotes": "This activity could not fit in the AI schedule.", "paymentStatus": "Pending", "clientVisibleNotes": "", "confirmationStatus": "Pending"}, {"id": "ad6ccd31-1d22-4dbe-b7aa-9ece5b4a270d", "name": "Travel back to Anuradhapura", "type": "travel", "endTime": "07:00 PM", "distance": "65 km", "dayNumber": 1, "startTime": "06:00 PM", "bufferMins": 15, "locationName": "Anuradhapura", "durationHours": 1, "internalNotes": "", "paymentStatus": "Pending", "clientVisibleNotes": "", "confirmationStatus": "Pending"}, {"id": "01fdff6d-7de6-4661-b0a7-5c4148544bc3", "name": "Check-in and relax at hotel", "type": "wait", "endTime": "07:30 PM", "dayNumber": 1, "startTime": "07:00 PM", "bufferMins": 15, "locationName": "Anuradhapura", "durationHours": 3.5, "internalNotes": "", "paymentStatus": "Pending", "clientVisibleNotes": "", "confirmationStatus": "Pending"}, {"id": "d8b8840e-c003-4d48-8ec4-5db9ee6f249d", "name": "Dinner", "type": "meal", "endTime": "09:00 PM", "dayNumber": 1, "startTime": "07:30 PM", "bufferMins": 15, "locationName": "Anuradhapura", "durationHours": 1.5, "internalNotes": "", "paymentStatus": "Pending", "clientVisibleNotes": "", "confirmationStatus": "Pending"}, {"id": "e4ca24c4-8541-4c08-ba7d-b78e69fa131b", "name": "Overnight in Anuradhapura", "type": "sleep", "endTime": "06:00 AM", "dayNumber": 1, "startTime": "09:00 PM", "bufferMins": 15, "locationName": "Anuradhapura", "durationHours": 9, "internalNotes": "", "paymentStatus": "Pending", "clientVisibleNotes": "", "confirmationStatus": "Pending"}, {"id": "1dee550a-68fa-4271-b336-4b39f3b52077", "name": "Breakfast", "type": "meal", "endTime": "09:00 AM", "dayNumber": 2, "startTime": "08:00 AM", "bufferMins": 15, "locationName": "Anuradhapura", "durationHours": 1, "internalNotes": "", "paymentStatus": "Pending", "clientVisibleNotes": "", "confirmationStatus": "Pending"}, {"id": "16ea252c-0ec2-4f38-8508-29f05b2bae8f", "lng": 80.404, "name": "Sacred City of Anuradhapura", "type": "activity", "endTime": "03:00 PM", "distance": null, "dayNumber": 2, "startTime": "09:00 AM", "bufferMins": 15, "locationName": "Anuradhapura", "durationHours": 6, "internalNotes": "", "paymentStatus": "Pending", "clientVisibleNotes": "", "confirmationStatus": "Pending"}, {"id": "30c60a10-9b22-4966-91e0-ab157528348c", "name": "Lunch", "type": "meal", "endTime": "04:00 PM", "dayNumber": 2, "startTime": "03:00 PM", "bufferMins": 15, "locationName": "Anuradhapura", "durationHours": 1, "internalNotes": "", "paymentStatus": "Pending", "clientVisibleNotes": "", "confirmationStatus": "Pending"}, {"id": "b2af2fa6-db7f-4b17-9b3e-07cc06eaf21c", "name": "Relaxation and leisure time", "type": "wait", "endTime": "07:30 PM", "dayNumber": 2, "startTime": "04:00 PM", "bufferMins": 15, "locationName": "Anuradhapura", "durationHours": 3.5, "internalNotes": "", "paymentStatus": "Pending", "clientVisibleNotes": "", "confirmationStatus": "Pending"}, {"id": "273dd534-cadf-436c-863d-bcbc15171628", "name": "Dinner", "type": "meal", "endTime": "09:00 PM", "dayNumber": 2, "startTime": "07:30 PM", "bufferMins": 15, "locationName": "Anuradhapura", "durationHours": 1.5, "internalNotes": "", "paymentStatus": "Pending", "clientVisibleNotes": "", "confirmationStatus": "Pending"}, {"id": "d24fc90e-0f5f-4c42-9c42-abf03c27446e", "name": "Overnight in Anuradhapura", "type": "sleep", "endTime": "06:00 AM", "dayNumber": 2, "startTime": "09:00 PM", "bufferMins": 15, "locationName": "Anuradhapura", "durationHours": 9, "internalNotes": "", "paymentStatus": "Pending", "clientVisibleNotes": "", "confirmationStatus": "Pending"}, {"id": "d459ac42-753d-4e93-9bb2-2e6781519633", "name": "Breakfast", "type": "meal", "endTime": "07:00 AM", "dayNumber": 3, "startTime": "06:00 AM", "bufferMins": 15, "locationName": "Anuradhapura", "durationHours": 1, "internalNotes": "", "paymentStatus": "Pending", "clientVisibleNotes": "", "confirmationStatus": "Pending"}, {"id": "36e19f4b-8515-4967-88fe-319b14a0abba", "name": "Travel to Sigiriya", "type": "travel", "endTime": "09:30 AM", "distance": "75 km", "dayNumber": 3, "startTime": "07:00 AM", "bufferMins": 15, "locationName": "Sigiriya", "durationHours": 2.5, "internalNotes": "", "paymentStatus": "Pending", "clientVisibleNotes": "", "confirmationStatus": "Pending"}, {"id": "1f972bdc-e1d8-499c-83c9-26beb99c17bc", "lng": 80.76, "name": "Visit Sigiriya Rock Fortress", "type": "activity", "endTime": "01:30 PM", "distance": null, "dayNumber": 3, "startTime": "09:30 AM", "bufferMins": 15, "locationName": "Sigiriya", "durationHours": 4, "internalNotes": "", "paymentStatus": "Pending", "clientVisibleNotes": "", "confirmationStatus": "Pending"}, {"id": "7aa47d3b-af13-4614-bd45-427a31626e08", "name": "Lunch", "type": "meal", "endTime": "02:30 PM", "dayNumber": 3, "startTime": "01:30 PM", "bufferMins": 15, "locationName": "Sigiriya", "durationHours": 1, "internalNotes": "", "paymentStatus": "Pending", "clientVisibleNotes": "", "confirmationStatus": "Pending"}, {"id": "c9daffe4-56a8-41b3-9431-560f678d0d03", "name": "Travel to Nuwara Eliya", "type": "travel", "endTime": "07:00 PM", "distance": "140 km", "dayNumber": 3, "startTime": "02:30 PM", "bufferMins": 15, "locationName": "Nuwara Eliya", "durationHours": 4.5, "internalNotes": "", "paymentStatus": "Pending", "clientVisibleNotes": "", "confirmationStatus": "Pending"}, {"id": "42f0464a-fa9b-4c2d-a5a8-c6b837b6ca6b", "name": "Dinner", "type": "meal", "endTime": "09:00 PM", "dayNumber": 3, "startTime": "07:30 PM", "bufferMins": 15, "locationName": "Nuwara Eliya", "durationHours": 1.5, "internalNotes": "", "paymentStatus": "Pending", "clientVisibleNotes": "", "confirmationStatus": "Pending"}, {"id": "40f3ca2e-85cf-47eb-ad77-239ce93d6f1e", "name": "Overnight in Nuwara Eliya", "type": "sleep", "endTime": "06:00 AM", "dayNumber": 3, "startTime": "09:00 PM", "bufferMins": 15, "locationName": "Nuwara Eliya", "durationHours": 9, "internalNotes": "", "paymentStatus": "Pending", "clientVisibleNotes": "", "confirmationStatus": "Pending"}, {"id": "184d5e77-d1d2-4851-9ab4-9841cd7471a1", "name": "Breakfast", "type": "meal", "endTime": "09:00 AM", "dayNumber": 4, "startTime": "08:00 AM", "bufferMins": 15, "locationName": "Nuwara Eliya", "durationHours": 1, "internalNotes": "", "paymentStatus": "Pending", "clientVisibleNotes": "", "confirmationStatus": "Pending"}, {"id": "a3332450-46a3-4e91-b04c-e402e53981a0", "lng": 80.8, "name": "Exploring the Hakgala Botanical Gardens", "type": "activity", "endTime": "11:00 AM", "distance": null, "dayNumber": 4, "startTime": "09:00 AM", "bufferMins": 15, "locationName": "Hakgala Botanical Gardens", "durationHours": 2, "internalNotes": "", "paymentStatus": "Pending", "clientVisibleNotes": "", "confirmationStatus": "Pending"}, {"id": "cff7c8af-84e6-48fa-a282-a7341424a6d4", "name": "Explore Nuwara Eliya town and surroundings", "type": "wait", "endTime": "01:00 PM", "dayNumber": 4, "startTime": "11:00 AM", "bufferMins": 15, "locationName": "Nuwara Eliya", "durationHours": 2, "internalNotes": "", "paymentStatus": "Pending", "clientVisibleNotes": "", "confirmationStatus": "Pending"}, {"id": "ba857300-0663-4660-94d2-d176ae328483", "name": "Lunch", "type": "meal", "endTime": "02:00 PM", "dayNumber": 4, "startTime": "01:00 PM", "bufferMins": 15, "locationName": "Nuwara Eliya", "durationHours": 1, "internalNotes": "", "paymentStatus": "Pending", "clientVisibleNotes": "", "confirmationStatus": "Pending"}, {"id": "0c47c1c2-e6b8-41f5-9884-4cfd5adc0b26", "name": "Visit a tea plantation and Gregory Lake", "type": "wait", "endTime": "07:30 PM", "dayNumber": 4, "startTime": "02:00 PM", "bufferMins": 15, "locationName": "Nuwara Eliya", "durationHours": 5.5, "internalNotes": "", "paymentStatus": "Pending", "clientVisibleNotes": "", "confirmationStatus": "Pending"}, {"id": "519b4fcb-de01-43c5-aec9-8fa8ffd5429f", "name": "Dinner", "type": "meal", "endTime": "09:00 PM", "dayNumber": 4, "startTime": "07:30 PM", "bufferMins": 15, "locationName": "Nuwara Eliya", "durationHours": 1.5, "internalNotes": "", "paymentStatus": "Pending", "clientVisibleNotes": "", "confirmationStatus": "Pending"}, {"id": "4e93b558-516e-4cc1-b143-2ecebdef6765", "name": "Overnight in Nuwara Eliya", "type": "sleep", "endTime": "06:00 AM", "dayNumber": 4, "startTime": "09:00 PM", "bufferMins": 15, "locationName": "Nuwara Eliya", "durationHours": 9, "internalNotes": "", "paymentStatus": "Pending", "clientVisibleNotes": "", "confirmationStatus": "Pending"}, {"id": "5b572119-59be-4841-bfac-18e1f001488d", "name": "Breakfast", "type": "meal", "endTime": "09:00 AM", "dayNumber": 5, "startTime": "08:00 AM", "bufferMins": 15, "locationName": "Nuwara Eliya", "durationHours": 1, "internalNotes": "", "paymentStatus": "Pending", "clientVisibleNotes": "", "confirmationStatus": "Pending"}, {"id": "a9aad177-53ed-43bf-b250-7a7da53ad889", "name": "Travel to Ella", "type": "travel", "endTime": "11:00 AM", "distance": "60 km", "dayNumber": 5, "startTime": "09:00 AM", "bufferMins": 15, "locationName": "Ella", "durationHours": 2, "internalNotes": "", "paymentStatus": "Pending", "clientVisibleNotes": "", "confirmationStatus": "Pending"}, {"id": "142b8317-ff37-40cb-8db2-1acfe2df7d2c", "name": "Check-in and settle into Ella accommodation", "type": "wait", "endTime": "01:00 PM", "dayNumber": 5, "startTime": "11:00 AM", "bufferMins": 15, "locationName": "Ella", "durationHours": 2, "internalNotes": "", "paymentStatus": "Pending", "clientVisibleNotes": "", "confirmationStatus": "Pending"}, {"id": "e06bb4bc-78b8-4c5e-981a-708b487ab698", "name": "Lunch", "type": "meal", "endTime": "02:00 PM", "dayNumber": 5, "startTime": "01:00 PM", "bufferMins": 15, "locationName": "Ella", "durationHours": 1, "internalNotes": "", "paymentStatus": "Pending", "clientVisibleNotes": "", "confirmationStatus": "Pending"}, {"id": "2095be5f-5e47-4e80-a603-8eb1e9db1868", "name": "Leisure time in Ella, explore local cafes or prepare for tomorrow's hike", "type": "wait", "endTime": "07:30 PM", "dayNumber": 5, "startTime": "02:00 PM", "bufferMins": 15, "locationName": "Ella", "durationHours": 5.5, "internalNotes": "", "paymentStatus": "Pending", "clientVisibleNotes": "", "confirmationStatus": "Pending"}, {"id": "5f7f0743-b0da-4700-88d5-c56a9f02b30d", "name": "Dinner", "type": "meal", "endTime": "09:00 PM", "dayNumber": 5, "startTime": "07:30 PM", "bufferMins": 15, "locationName": "Ella", "durationHours": 1.5, "internalNotes": "", "paymentStatus": "Pending", "clientVisibleNotes": "", "confirmationStatus": "Pending"}, {"id": "eee85710-9e62-4a49-b740-536b43116a1a", "name": "Overnight in Ella", "type": "sleep", "endTime": "05:00 AM", "dayNumber": 5, "startTime": "09:00 PM", "bufferMins": 15, "locationName": "Ella", "durationHours": 8, "internalNotes": "", "paymentStatus": "Pending", "clientVisibleNotes": "", "confirmationStatus": "Pending"}, {"id": "56a90c97-8a8d-4b73-8e06-2ccadf4ee2b0", "lng": 81.0465, "name": "Hiking Ella Rock", "type": "activity", "endTime": "10:30 AM", "distance": null, "dayNumber": 6, "startTime": "05:30 AM", "bufferMins": 15, "locationName": "Ella Rock", "durationHours": 5, "internalNotes": "", "paymentStatus": "Pending", "clientVisibleNotes": "", "confirmationStatus": "Pending"}, {"id": "29fdc2c9-0526-4ac9-a62b-6050b85c9f50", "name": "Breakfast/Brunch after hike", "type": "meal", "endTime": "11:30 AM", "dayNumber": 6, "startTime": "10:30 AM", "bufferMins": 15, "locationName": "Ella", "durationHours": 1, "internalNotes": "", "paymentStatus": "Pending", "clientVisibleNotes": "", "confirmationStatus": "Pending"}, {"id": "546c81f1-5fed-4f1f-88ab-a8e3d97cd764", "name": "Travel to Udawalawe", "type": "travel", "endTime": "02:30 PM", "distance": "90 km", "dayNumber": 6, "startTime": "11:30 AM", "bufferMins": 15, "locationName": "Udawalawe", "durationHours": 3, "internalNotes": "", "paymentStatus": "Pending", "clientVisibleNotes": "", "confirmationStatus": "Pending"}, {"id": "ddfe3a34-21ee-4b09-b956-c3cac1f00f8c", "name": "Lunch", "type": "meal", "endTime": "03:30 PM", "dayNumber": 6, "startTime": "02:30 PM", "bufferMins": 15, "locationName": "Udawalawe", "durationHours": 1, "internalNotes": "", "paymentStatus": "Pending", "clientVisibleNotes": "", "confirmationStatus": "Pending"}, {"id": "bc65cc09-6a4d-40ba-a894-4d415d942a7c", "name": "Relaxation at hotel, prepare for Elephant Transit Home visit", "type": "wait", "endTime": "07:30 PM", "dayNumber": 6, "startTime": "03:30 PM", "bufferMins": 15, "locationName": "Udawalawe", "durationHours": 4, "internalNotes": "", "paymentStatus": "Pending", "clientVisibleNotes": "", "confirmationStatus": "Pending"}, {"id": "314bee9e-7885-43ea-9ae7-5efd63337f00", "name": "Dinner", "type": "meal", "endTime": "09:00 PM", "dayNumber": 6, "startTime": "07:30 PM", "bufferMins": 15, "locationName": "Udawalawe", "durationHours": 1.5, "internalNotes": "", "paymentStatus": "Pending", "clientVisibleNotes": "", "confirmationStatus": "Pending"}, {"id": "a1b648cf-f609-4523-837c-6692d5bb7e8e", "name": "Overnight in Udawalawe", "type": "sleep", "endTime": "06:00 AM", "dayNumber": 6, "startTime": "09:00 PM", "bufferMins": 15, "locationName": "Udawalawe", "durationHours": 9, "internalNotes": "", "paymentStatus": "Pending", "clientVisibleNotes": "", "confirmationStatus": "Pending"}, {"id": "05b4a7d5-72e8-4534-bdac-ed6fba26ae1a", "name": "Breakfast", "type": "meal", "endTime": "09:00 AM", "dayNumber": 7, "startTime": "08:00 AM", "bufferMins": 15, "locationName": "Udawalawe", "durationHours": 1, "internalNotes": "", "paymentStatus": "Pending", "clientVisibleNotes": "", "confirmationStatus": "Pending"}, {"id": "9f1fa68f-8de6-41f2-bc3b-ade6d80a8c8c", "lng": 80.881, "name": "Visiting the Elephant Transit Home in Udawalawe", "type": "activity", "endTime": "10:30 AM", "distance": null, "dayNumber": 7, "startTime": "09:00 AM", "bufferMins": 15, "locationName": "Udawalawe Elephant Transit Home", "durationHours": 1.5, "internalNotes": "", "paymentStatus": "Pending", "clientVisibleNotes": "", "confirmationStatus": "Pending"}, {"id": "53573dde-cebd-48ef-ad08-4fc425219cee", "name": "Travel to Galle", "type": "travel", "endTime": "01:30 PM", "distance": "100 km", "dayNumber": 7, "startTime": "10:30 AM", "bufferMins": 15, "locationName": "Galle", "durationHours": 3, "internalNotes": "", "paymentStatus": "Pending", "clientVisibleNotes": "", "confirmationStatus": "Pending"}, {"id": "9243c483-c1f8-4bdb-8b15-7b6fa293cac3", "name": "Lunch", "type": "meal", "endTime": "02:30 PM", "dayNumber": 7, "startTime": "01:30 PM", "bufferMins": 15, "locationName": "Galle", "durationHours": 1, "internalNotes": "", "paymentStatus": "Pending", "clientVisibleNotes": "", "confirmationStatus": "Pending"}, {"id": "5b896195-c1e3-4110-8ebb-680bdcfc2fb9", "lng": 80.2168, "name": "Learning to Make Hoppers (Galle)", "type": "activity", "endTime": "05:30 PM", "distance": null, "dayNumber": 7, "startTime": "03:00 PM", "bufferMins": 15, "locationName": "Galle", "durationHours": 2.5, "internalNotes": "", "paymentStatus": "Pending", "clientVisibleNotes": "", "confirmationStatus": "Pending"}, {"id": "02cbe4b2-a2b8-482f-8082-0a33e1924326", "name": "Explore Galle Fort and enjoy the sunset", "type": "wait", "endTime": "07:30 PM", "dayNumber": 7, "startTime": "05:30 PM", "bufferMins": 15, "locationName": "Galle", "durationHours": 2, "internalNotes": "", "paymentStatus": "Pending", "clientVisibleNotes": "", "confirmationStatus": "Pending"}, {"id": "60bcecfb-0207-4882-8fd4-30b428e8925e", "name": "Dinner", "type": "meal", "endTime": "09:00 PM", "dayNumber": 7, "startTime": "07:30 PM", "bufferMins": 15, "locationName": "Galle", "durationHours": 1.5, "internalNotes": "", "paymentStatus": "Pending", "clientVisibleNotes": "", "confirmationStatus": "Pending"}, {"id": "73c9e65f-a6e2-4af6-91bd-ca06fa371a20", "name": "Overnight in Galle", "type": "sleep", "endTime": "06:00 AM", "dayNumber": 7, "startTime": "09:00 PM", "bufferMins": 15, "locationName": "Galle", "durationHours": 9, "internalNotes": "", "paymentStatus": "Pending", "clientVisibleNotes": "", "confirmationStatus": "Pending"}, {"id": "c49265c9-3b87-4d08-bd64-e6cd432363a5", "name": "Breakfast", "type": "meal", "endTime": "09:00 AM", "dayNumber": 8, "startTime": "08:00 AM", "bufferMins": 15, "locationName": "Galle", "durationHours": 1, "internalNotes": "", "paymentStatus": "Pending", "clientVisibleNotes": "", "confirmationStatus": "Pending"}, {"id": "d236d959-6e49-4912-953b-18b0c36d601f", "name": "Morning leisure in Galle Fort, last-minute souvenir shopping", "type": "wait", "endTime": "12:00 PM", "dayNumber": 8, "startTime": "09:00 AM", "bufferMins": 15, "locationName": "Galle", "durationHours": 3, "internalNotes": "", "paymentStatus": "Pending", "clientVisibleNotes": "", "confirmationStatus": "Pending"}, {"id": "19d92325-86b8-4c3b-bd11-691f4d038964", "name": "Lunch", "type": "meal", "endTime": "01:00 PM", "dayNumber": 8, "startTime": "12:00 PM", "bufferMins": 15, "locationName": "Galle", "durationHours": 1, "internalNotes": "", "paymentStatus": "Pending", "clientVisibleNotes": "", "confirmationStatus": "Pending"}, {"id": "3686caba-9f3e-435b-a943-1be6889fb45e", "name": "Travel to Katunayake Airport (KTA)", "type": "travel", "endTime": "06:00 PM", "distance": "160 km", "dayNumber": 8, "startTime": "01:00 PM", "bufferMins": 15, "locationName": "Katunayake Airport", "durationHours": 5, "internalNotes": "", "paymentStatus": "Pending", "clientVisibleNotes": "", "confirmationStatus": "Pending"}, {"id": "9d67a378-edf8-4e58-a01c-4aab3df223fa", "name": "Departure from KTA", "type": "wait", "endTime": "08:00 PM", "dayNumber": 8, "startTime": "06:00 PM", "bufferMins": 15, "locationName": "Katunayake Airport", "durationHours": 2, "internalNotes": "", "paymentStatus": "Pending", "clientVisibleNotes": "", "confirmationStatus": "Pending"}], "travelers": [{"id": "99a13c87-bd89-45ed-b81f-7da4a410c5ca", "fullName": "Jane Doe", "nationality": "USA", "medicalNotes": "", "passportNumber": "US123456", "roomPreference": "Double", "dietaryPreferences": "Vegetarian"}, {"id": "91b37090-2605-44a0-aedb-1d232fd6d65c", "fullName": "John Doe", "nationality": "USA", "medicalNotes": "Pacemaker", "passportNumber": "US654321", "roomPreference": "Double", "dietaryPreferences": "None"}, {"id": "a69f878a-a07b-4bbb-947f-91d97c55caae", "fullName": "Alice Smith", "nationality": "UK", "medicalNotes": "", "passportNumber": "UK98765", "roomPreference": "Single", "dietaryPreferences": ""}], "activities": [{"id": "445fbde9-056f-4427-a9e2-3fb6a6010dfe", "status": "Random / Walk-in", "activityId": 10, "cutOffDate": "", "activityData": {"id": 10, "lat": 6.8667, "lng": 81.0465, "images": ["/images/activities/hiking_ella_rock_1.avif", "/images/activities/hiking_ella_rock_2.avif", "/images/activities/hiking_ella_rock_3.avif"], "category": "Adventure", "district": "Badulla", "created_at": "2026-02-25T08:48:21.173089+00:00", "description": "Embark on a rewarding half-day hike through tea plantations and jungle to reach the summit of Ella Rock for spectacular views. Allow time for photos and enjoying the panorama.", "activity_name": "Hiking Ella Rock", "location_name": "Ella", "time_flexible": false, "duration_hours": 5, "optimal_end_time": "18:30:00", "optimal_start_time": "05:30:00"}, "paymentTerms": "", "bookingReference": "", "supplierContactPerson": ""}, {"id": "c3c72c1d-5d70-4f05-81ce-6ea5590aac91", "status": "Random / Walk-in", "activityId": 105, "cutOffDate": "", "activityData": {"id": 105, "lat": 7.957, "lng": 80.76, "images": ["/images/activities/climbing_sigiriya_rock_1.avif", "/images/activities/climbing_sigiriya_rock_2.avif", "/images/activities/climbing_sigiriya_rock_3.avif"], "category": "Cultural", "district": "Matale", "created_at": "2026-03-06T17:31:06.928826+00:00", "description": "Climb the ancient rock fortress with frescoes and lion gate. UNESCO World Heritage site with breathtaking views from the summit.", "activity_name": "Visit Sigiriya Rock Fortress", "location_name": "Sigiriya", "time_flexible": false, "duration_hours": 4, "optimal_end_time": "11:00:00", "optimal_start_time": "07:00:00"}, "paymentTerms": "", "bookingReference": "", "supplierContactPerson": ""}, {"id": "1ee826ef-d4de-4489-872a-aecd04ab6411", "status": "Random / Walk-in", "activityId": 93, "cutOffDate": "", "activityData": {"id": 93, "lat": 6.457, "lng": 80.881, "images": ["/images/activities/elephant_transit_home_1_1773572565987.avif", "/images/activities/elephant_transit_home_2_1773572599066.avif", "/images/activities/elephant_transit_home_3_1773572615806.avif"], "category": "Nature & Wildlife", "district": "Ratnapura", "created_at": "2026-02-25T08:48:21.173089+00:00", "description": "Watch orphaned elephants being fed and cared for at the Elephant Transit Home in Udawalawe, a rehabilitation center that releases them back into the wild. Feeding times are scheduled.", "activity_name": "Visiting the Elephant Transit Home in Udawalawe", "location_name": "Udawalawe", "time_flexible": false, "duration_hours": 1.5, "optimal_end_time": "12:00:00", "optimal_start_time": "09:00:00"}, "paymentTerms": "", "bookingReference": "", "supplierContactPerson": ""}, {"id": "d74dcb69-1005-4aa5-8e21-9f6ab7e6d5ae", "status": "Random / Walk-in", "activityId": 79, "cutOffDate": "", "activityData": {"id": 79, "lat": 6.0329, "lng": 80.2168, "images": ["/images/activities/cooking_class_colombo_1.avif", "/images/activities/cooking_class_colombo_2.avif", "/images/activities/cooking_class_colombo_3.avif"], "category": "Food & Drink", "district": "Galle", "created_at": "2026-02-25T08:48:21.173089+00:00", "description": "Take a short workshop to learn how to make appa (hoppers) – the bowl-shaped rice flour crepes that are a breakfast staple – from a local chef.", "activity_name": "Learning to Make Hoppers (Galle)", "location_name": "Galle", "time_flexible": false, "duration_hours": 2.5, "optimal_end_time": "12:00:00", "optimal_start_time": "09:30:00"}, "paymentTerms": "", "bookingReference": "", "supplierContactPerson": ""}, {"id": "161450c2-230b-4f3c-a3cb-655c907b04ac", "status": "Random / Walk-in", "activityId": 97, "cutOffDate": "", "activityData": {"id": 97, "lat": 6.9167, "lng": 80.8, "images": ["/images/activities/peradeniya_botanical_gardens_1.avif", "/images/activities/peradeniya_botanical_gardens_2.avif", "/images/activities/peradeniya_botanical_gardens_3.avif"], "category": "Nature & Wildlife", "district": "Nuwara Eliya", "created_at": "2026-02-25T08:48:21.173089+00:00", "description": "Wander through these cool-climate gardens in Nuwara Eliya, which once served as a trial ground for cinchona and tea cultivation. Best in morning for crisp mountain air.", "activity_name": "Exploring the Hakgala Botanical Gardens", "location_name": "Hakgala", "time_flexible": false, "duration_hours": 2, "optimal_end_time": "09:30:00", "optimal_start_time": "07:30:00"}, "paymentTerms": "", "bookingReference": "", "supplierContactPerson": ""}, {"id": "7e87c2a5-3ec4-4c4a-a7e9-2c7edafc43fc", "status": "Random / Walk-in", "activityId": 109, "cutOffDate": "", "activityData": {"id": 109, "lat": 8.311, "lng": 80.404, "images": ["/images/activities/temple_of_the_tooth_1.avif", "/images/activities/temple_of_the_tooth_2.avif", "/images/activities/temple_of_the_tooth_3.avif"], "category": "Cultural", "district": "Anuradhapura", "created_at": "2026-03-06T17:31:06.928826+00:00", "description": "Discover ancient Buddhist civilization with massive stupas, monasteries, and the sacred Bodhi Tree.", "activity_name": "Sacred City of Anuradhapura", "location_name": "Anuradhapura", "time_flexible": false, "duration_hours": 6, "optimal_end_time": "18:00:00", "optimal_start_time": "06:30:00"}, "paymentTerms": "", "bookingReference": "", "supplierContactPerson": ""}, {"id": "ac310907-7c18-4f02-9740-213deb40e55b", "status": "Random / Walk-in", "activityId": 112, "cutOffDate": "", "activityData": {"id": 112, "lat": 8.581, "lng": 81.245, "images": ["/images/activities/temple_of_the_tooth_1.avif", "/images/activities/temple_of_the_tooth_2.avif", "/images/activities/temple_of_the_tooth_3.avif"], "category": "Cultural", "district": "Trincomalee", "created_at": "2026-03-06T17:31:06.928826+00:00", "description": "Ancient Hindu temple on Swami Rock cliff with spectacular ocean views and religious significance.", "activity_name": "Koneswaram Temple", "location_name": "Trincomalee", "time_flexible": false, "duration_hours": 1.5, "optimal_end_time": "12:00:00", "optimal_start_time": "06:00:00"}, "paymentTerms": "", "bookingReference": "", "supplierContactPerson": ""}], "clientName": "Supun Ratnaweera", "financials": {"costs": {"tax": 0, "misc": 0, "guide": 0, "hotels": 0, "flights": 0, "transport": 0, "activities": 0, "commission": 0}, "sellingPrice": 12000, "purchaseOrders": [], "supplierInvoices": []}, "transports": [{"id": "6266c0ca-573c-450d-8171-8645b79a1726", "mode": "SMALL_PREMIUM_SEDAN", "status": "Tentative", "supplier": "", "driverName": "", "contractUrl": "", "guideDetails": "", "driverContact": "", "guideAssigned": true, "paymentStatus": "Pending", "vehicleNumber": "", "bookingReference": ""}, {"id": "7b1f1a5f-4922-402b-b4d3-5d8b64682a84", "mode": "SMALL_PREMIUM_SEDAN", "status": "Tentative", "supplier": "", "driverName": "", "contractUrl": "", "guideDetails": "", "driverContact": "", "guideAssigned": true, "paymentStatus": "Pending", "vehicleNumber": "", "bookingReference": ""}, {"id": "58e5580c-5d28-4fd9-a15a-576481fbf5ef", "mode": "SMALL_PREMIUM_SEDAN", "status": "Tentative", "supplier": "", "driverName": "", "contractUrl": "", "guideDetails": "", "driverContact": "", "guideAssigned": true, "paymentStatus": "Pending", "vehicleNumber": "", "bookingReference": ""}, {"id": "1babc541-0bf8-4ad1-96f8-32cb75953ec1", "mode": "SMALL_PREMIUM_SEDAN", "status": "Tentative", "supplier": "", "driverName": "", "contractUrl": "", "guideDetails": "", "driverContact": "", "guideAssigned": true, "paymentStatus": "Pending", "vehicleNumber": "", "bookingReference": ""}, {"id": "e11c8ef9-6351-47bf-b919-2d86b2c3c96c", "mode": "SMALL_PREMIUM_SEDAN", "status": "Tentative", "supplier": "", "driverName": "", "contractUrl": "", "guideDetails": "", "driverContact": "", "guideAssigned": true, "paymentStatus": "Pending", "vehicleNumber": "", "bookingReference": ""}, {"id": "90212bdc-00aa-4015-abf9-c32c46b16a55", "mode": "SMALL_PREMIUM_SEDAN", "status": "Tentative", "supplier": "", "driverName": "", "contractUrl": "", "guideDetails": "", "driverContact": "", "guideAssigned": true, "paymentStatus": "Pending", "vehicleNumber": "", "bookingReference": ""}, {"id": "60b10d21-2908-49ce-8342-f4820ac2a0ec", "mode": "SMALL_PREMIUM_SEDAN", "status": "Tentative", "supplier": "", "driverName": "", "contractUrl": "", "guideDetails": "", "driverContact": "", "guideAssigned": true, "paymentStatus": "Pending", "vehicleNumber": "", "bookingReference": ""}, {"id": "6d87618c-64e5-4f35-bbb7-27c65a6b21f9", "mode": "SMALL_PREMIUM_SEDAN", "status": "Tentative", "supplier": "", "driverName": "", "contractUrl": "", "guideDetails": "", "driverContact": "", "guideAssigned": true, "paymentStatus": "Pending", "vehicleNumber": "", "bookingReference": ""}], "clientEmail": "admin@nilathra.com", "clientPhone": "+94 0773887502", "serviceScopes": ["Book International Flights", "Plan Activities & Experiences", "Visa Assistance"], "accommodations": [{"id": "a1f7bf1c-1f49-4534-80f4-67f9c71353ad", "email": "", "status": "Tentative", "address": "Ella", "hotelId": "9aa336f0-4be4-453b-be67-a30996432c08", "mapLink": "", "mealPlan": "BB", "hotelName": "98 Acres Resort", "stayClass": "5 Star", "nightIndex": 1, "rateCardUrl": "", "roomStandard": "Standard Room", "contactNumber": "+94 11 1414141", "contactPerson": "Res", "numberOfRooms": 1, "paymentStatus": "Pending", "pricePerNight": 0, "specialRequests": "", "beddingConfiguration": "", "cancellationDeadline": "", "confirmationReference": ""}, {"id": "34c9dbb2-918e-41a1-837e-52455e610b4e", "email": "", "status": "Tentative", "address": "Ella", "hotelId": "9aa336f0-4be4-453b-be67-a30996432c08", "mapLink": "", "mealPlan": "BB", "hotelName": "98 Acres Resort", "stayClass": "5 Star", "nightIndex": 2, "rateCardUrl": "", "roomStandard": "Standard Room", "contactNumber": "+94 11 1414141", "contactPerson": "Res", "numberOfRooms": 1, "paymentStatus": "Pending", "pricePerNight": 0, "specialRequests": "", "beddingConfiguration": "", "cancellationDeadline": "", "confirmationReference": ""}, {"id": "8f7dcc6f-ec24-4a8c-95c9-b136d60c2f43", "email": "", "status": "Tentative", "address": "Ella", "hotelId": "9aa336f0-4be4-453b-be67-a30996432c08", "mapLink": "", "mealPlan": "BB", "hotelName": "98 Acres Resort", "stayClass": "5 Star", "nightIndex": 3, "rateCardUrl": "", "roomStandard": "Standard Room", "contactNumber": "+94 11 1414141", "contactPerson": "Res", "numberOfRooms": 1, "paymentStatus": "Pending", "pricePerNight": 0, "specialRequests": "", "beddingConfiguration": "", "cancellationDeadline": "", "confirmationReference": ""}, {"id": "924ea04e-1360-4c3b-977f-da5d2a70d126", "email": "", "status": "Tentative", "address": "Ella", "hotelId": "9aa336f0-4be4-453b-be67-a30996432c08", "mapLink": "", "mealPlan": "BB", "hotelName": "98 Acres Resort", "stayClass": "5 Star", "nightIndex": 4, "rateCardUrl": "", "roomStandard": "Standard Room", "contactNumber": "+94 11 1414141", "contactPerson": "Res", "numberOfRooms": 1, "paymentStatus": "Pending", "pricePerNight": 0, "specialRequests": "", "beddingConfiguration": "", "cancellationDeadline": "", "confirmationReference": ""}, {"id": "688a9be1-61a6-4186-8acd-9ac3094db1b5", "email": "", "status": "Tentative", "address": "Ella", "hotelId": "9aa336f0-4be4-453b-be67-a30996432c08", "mapLink": "", "mealPlan": "BB", "hotelName": "98 Acres Resort", "stayClass": "5 Star", "nightIndex": 5, "rateCardUrl": "", "roomStandard": "Standard Room", "contactNumber": "+94 11 1414141", "contactPerson": "Res", "numberOfRooms": 1, "paymentStatus": "Pending", "pricePerNight": 0, "specialRequests": "", "beddingConfiguration": "", "cancellationDeadline": "", "confirmationReference": ""}, {"id": "9a80b0f5-da43-4876-8b0a-b84fe6753436", "email": "", "status": "Tentative", "address": "Ella", "hotelId": "9aa336f0-4be4-453b-be67-a30996432c08", "mapLink": "", "mealPlan": "BB", "hotelName": "98 Acres Resort", "stayClass": "5 Star", "nightIndex": 6, "rateCardUrl": "", "roomStandard": "Standard Room", "contactNumber": "+94 11 1414141", "contactPerson": "Res", "numberOfRooms": 1, "paymentStatus": "Pending", "pricePerNight": 0, "specialRequests": "", "beddingConfiguration": "", "cancellationDeadline": "", "confirmationReference": ""}, {"id": "dcc0a27d-0f3f-4d10-a97d-33328f3ce79a", "email": "", "status": "Tentative", "address": "Ella", "hotelId": "9aa336f0-4be4-453b-be67-a30996432c08", "mapLink": "", "mealPlan": "BB", "hotelName": "98 Acres Resort", "stayClass": "5 Star", "nightIndex": 7, "rateCardUrl": "", "roomStandard": "Standard Room", "contactNumber": "+94 11 1414141", "contactPerson": "Res", "numberOfRooms": 1, "paymentStatus": "Pending", "pricePerNight": 0, "specialRequests": "", "beddingConfiguration": "", "cancellationDeadline": "", "confirmationReference": ""}, {"id": "b39da305-e364-498b-bdea-35cc50ee68b9", "email": "", "status": "Tentative", "address": "Ella", "hotelId": "9aa336f0-4be4-453b-be67-a30996432c08", "mapLink": "", "mealPlan": "BB", "hotelName": "98 Acres Resort", "stayClass": "5 Star", "nightIndex": 8, "rateCardUrl": "", "roomStandard": "Standard Room", "contactNumber": "+94 11 1414141", "contactPerson": "Res", "numberOfRooms": 1, "paymentStatus": "Pending", "pricePerNight": 0, "specialRequests": "", "beddingConfiguration": "", "cancellationDeadline": "", "confirmationReference": ""}]}}]